httplib.py
pyhttplib-2.2.0.data/data/VERSION
pyhttplib-2.2.0.dist-info/licenses/COPYING.md
pyhttplib-2.2.0.dist-info/METADATA
pyhttplib-2.2.0.dist-info/WHEEL
pyhttplib-2.2.0.dist-info/top_level.txt
pyhttplib-2.2.0.dist-info/RECORD
