Metadata-Version: 2.4
Name: pyhttplib
Version: 2.2.0
Summary: pyhttplib
Home-page: https://github.com/Omena0/http
Author: Omena0
License: PolyForm Noncommercial 1.0.0
Classifier: Programming Language :: Python :: 3
Classifier: Programming Language :: Python :: 3.13
Classifier: License :: Other/Proprietary License
Classifier: Operating System :: OS Independent
Requires-Python: >=3.8
License-File: COPYING.md
Dynamic: description
Dynamic: description-content-type
Dynamic: license-file
Dynamic: summary
